[
    {
        "id": "78d47f8f-60f1-4d52-b0e2-d47b362c44d4",
        "plantName": "Mucronleaf Tortula Moss",
        "scientificName": "Tortula mucronifolia Schwägr.",
        "family": "Pottiaceae",
        "wateringFrequency": "Monthly",
        "lightRequirement": "low light",
        "temperatureRange": "cool",
        "soilType": "sandy",
        "fertilizerFrequency": "Daily",
        "bloomingSeason": "winter",
        "height": 82.7
    },
    {
        "id": "0687850c-20db-41b5-b8c0-97559a041002",
        "plantName": "Hawai'i Sedge",
        "scientificName": "Carex alligata Boott",
        "family": "Cyperaceae",
        "wateringFrequency": "Never",
        "lightRequirement": "high light",
        "temperatureRange": "cool",
        "soilType": "loamy",
        "fertilizerFrequency": "Once",
        "bloomingSeason": "winter",
        "height": 55.07
    },
    {
        "id": "9ee4b8c9-4c53-42f2-88ce-32a84ee72346",
        "plantName": "Disc Lichen",
        "scientificName": "Buellia insignis (Nageli ex Hepp) Th. Fr.",
        "family": "Physciaceae",
        "wateringFrequency": "Yearly",
        "lightRequirement": "high light",
        "temperatureRange": "cool",
        "soilType": "clay",
        "fertilizerFrequency": "Monthly",
        "bloomingSeason": "fall",
        "height": 46.55
    },
    {
        "id": "c06e270b-43a0-44fa-8a5c-6cdd6c637a57",
        "plantName": "Bush Beardtongue",
        "scientificName": "Keckiella breviflora (Lindl.) Straw",
        "family": "Scrophulariaceae",
        "wateringFrequency": "Weekly",
        "lightRequirement": "medium light",
        "temperatureRange": "warm",
        "soilType": "loamy",
        "fertilizerFrequency": "Weekly",
        "bloomingSeason": "spring",
        "height": 14.63
    },
    {
        "id": "8944a012-efb8-4103-b7db-75947d41c1d2",
        "plantName": "Arizona Bugbane",
        "scientificName": "Actaea arizonica (S. Watson) J. Compton",
        "family": "Ranunculaceae",
        "wateringFrequency": "Once",
        "lightRequirement": "high light",
        "temperatureRange": "moderate",
        "soilType": "loamy",
        "fertilizerFrequency": "Weekly",
        "bloomingSeason": "fall",
        "height": 96.45
    },
    {
        "id": "aa8a41c2-9b9d-4bac-9bc5-da2cb927b983",
        "plantName": "Racemed Fiestaflower",
        "scientificName": "Pholistoma racemosum (Nutt. ex A. Gray) Constance",
        "family": "Hydrophyllaceae",
        "wateringFrequency": "Never",
        "lightRequirement": "high light",
        "temperatureRange": "warm",
        "soilType": "clay",
        "fertilizerFrequency": "Often",
        "bloomingSeason": "spring",
        "height": 34
    },
    {
        "id": "cecb7560-a63d-4c60-bcb9-f5f4d79a4daf",
        "plantName": "Alpine Balsam",
        "scientificName": "Erinus alpinus L.",
        "family": "Scrophulariaceae",
        "wateringFrequency": "Often",
        "lightRequirement": "high light",
        "temperatureRange": "cool",
        "soilType": "loamy",
        "fertilizerFrequency": "Never",
        "bloomingSeason": "winter",
        "height": 41.27
    },
    {
        "id": "0c777ab0-d520-4c55-81d9-2cb28d120ac4",
        "plantName": "Klamath Manzanita",
        "scientificName": "Arctostaphylos klamathensis S.W. Edwards, Keeler-Wolf & W. Knight",
        "family": "Ericaceae",
        "wateringFrequency": "Monthly",
        "lightRequirement": "high light",
        "temperatureRange": "cool",
        "soilType": "sandy",
        "fertilizerFrequency": "Often",
        "bloomingSeason": "winter",
        "height": 42.25
    },
    {
        "id": "762d1c94-fdd1-459f-8deb-004b4cabd993",
        "plantName": "Tundra Fleabane",
        "scientificName": "Erigeron hyperboreus Greene",
        "family": "Asteraceae",
        "wateringFrequency": "Yearly",
        "lightRequirement": "medium light",
        "temperatureRange": "cool",
        "soilType": "loamy",
        "fertilizerFrequency": "Monthly",
        "bloomingSeason": "winter",
        "height": 72.29
    },
    {
        "id": "46bfeba7-e099-4b03-959d-a706c523ef74",
        "plantName": "Thunberg's Amaranthus",
        "scientificName": "Amaranthus thunbergii Moq.",
        "family": "Amaranthaceae",
        "wateringFrequency": "Once",
        "lightRequirement": "low light",
        "temperatureRange": "cool",
        "soilType": "loamy",
        "fertilizerFrequency": "Often",
        "bloomingSeason": "fall",
        "height": 16
    },
    {
        "id": "00d70107-333b-4b82-ad42-5f3e467c16a2",
        "plantName": "Guaje",
        "scientificName": "Leucaena esculenta (Sessé & Moc.) Benth.",
        "family": "Fabaceae",
        "wateringFrequency": "Never",
        "lightRequirement": "low light",
        "temperatureRange": "warm",
        "soilType": "sandy",
        "fertilizerFrequency": "Daily",
        "bloomingSeason": "summer",
        "height": 2.99
    },
    {
        "id": "bc6be551-dc18-4730-819c-638660b9a634",
        "plantName": "Common Bugle",
        "scientificName": "Ajuga reptans L.",
        "family": "Lamiaceae",
        "wateringFrequency": "Daily",
        "lightRequirement": "medium light",
        "temperatureRange": "warm",
        "soilType": "clay",
        "fertilizerFrequency": "Monthly",
        "bloomingSeason": "summer",
        "height": 32.27
    },
    {
        "id": "891dcba2-9d16-4bdb-aa4f-c83828d12db2",
        "plantName": "Common Rue",
        "scientificName": "Ruta graveolens L.",
        "family": "Rutaceae",
        "wateringFrequency": "Monthly",
        "lightRequirement": "medium light",
        "temperatureRange": "cool",
        "soilType": "clay",
        "fertilizerFrequency": "Yearly",
        "bloomingSeason": "winter",
        "height": 16.76
    },
    {
        "id": "4b5eec6e-2e39-41a6-8c11-949acb942666",
        "plantName": "St. John's Bread",
        "scientificName": "Ceratonia siliqua L.",
        "family": "Fabaceae",
        "wateringFrequency": "Daily",
        "lightRequirement": "low light",
        "temperatureRange": "warm",
        "soilType": "sandy",
        "fertilizerFrequency": "Once",
        "bloomingSeason": "summer",
        "height": 54.12
    },
    {
        "id": "c3ed85ad-c3d3-4118-8d26-3264d7ae328d",
        "plantName": "Chilean Chess",
        "scientificName": "Bromus berteroanus Colla",
        "family": "Poaceae",
        "wateringFrequency": "Often",
        "lightRequirement": "medium light",
        "temperatureRange": "warm",
        "soilType": "loamy",
        "fertilizerFrequency": "Often",
        "bloomingSeason": "summer",
        "height": 25.75
    },
    {
        "id": "b4cd4a32-3778-448d-b0cc-97b4a4e4b4ad",
        "plantName": "Goldenwave Tickseed",
        "scientificName": "Coreopsis intermedia Sherff",
        "family": "Asteraceae",
        "wateringFrequency": "Often",
        "lightRequirement": "high light",
        "temperatureRange": "moderate",
        "soilType": "clay",
        "fertilizerFrequency": "Monthly",
        "bloomingSeason": "winter",
        "height": 64.61
    },
    {
        "id": "a3fc9a83-b5e5-49e9-a1c8-cb7ac8a4bf99",
        "plantName": "Maidenhair Fern",
        "scientificName": "Adiantum ×tracyi C.C. Hall ex W.H. Wagner",
        "family": "Pteridaceae",
        "wateringFrequency": "Never",
        "lightRequirement": "low light",
        "temperatureRange": "moderate",
        "soilType": "clay",
        "fertilizerFrequency": "Often",
        "bloomingSeason": "fall",
        "height": 14.57
    },
    {
        "id": "2d4aad69-b12c-4301-8839-89d2d64d4056",
        "plantName": "Hopea",
        "scientificName": "Hopea micrantha Hook. f.",
        "family": "Dipterocarpaceae",
        "wateringFrequency": "Daily",
        "lightRequirement": "low light",
        "temperatureRange": "cool",
        "soilType": "clay",
        "fertilizerFrequency": "Once",
        "bloomingSeason": "spring",
        "height": 11.95
    },
    {
        "id": "482aef2e-35b5-4216-89d7-da3e7b0a0193",
        "plantName": "Snow Lichen",
        "scientificName": "Stereocaulon myriocarpum Th. Fr.",
        "family": "Stereocaulaceae",
        "wateringFrequency": "Daily",
        "lightRequirement": "medium light",
        "temperatureRange": "cool",
        "soilType": "clay",
        "fertilizerFrequency": "Often",
        "bloomingSeason": "spring",
        "height": 47.85
    },
    {
        "id": "3a6bf170-f7f7-4702-a80b-f99208ab33a5",
        "plantName": "Netleaf Willow",
        "scientificName": "Salix reticulata L.",
        "family": "Salicaceae",
        "wateringFrequency": "Weekly",
        "lightRequirement": "high light",
        "temperatureRange": "moderate",
        "soilType": "sandy",
        "fertilizerFrequency": "Weekly",
        "bloomingSeason": "summer",
        "height": 72.09
    },
    {
        "id": "7717205e-00a5-4d8a-ba4a-b52ec2e2122e",
        "plantName": "Greeneye Heliotrope",
        "scientificName": "Heliotropium glabriusculum (Torr.) A. Gray",
        "family": "Boraginaceae",
        "wateringFrequency": "Often",
        "lightRequirement": "low light",
        "temperatureRange": "cool",
        "soilType": "sandy",
        "fertilizerFrequency": "Yearly",
        "bloomingSeason": "winter",
        "height": 36.99
    },
    {
        "id": "3ae72b0e-301e-4630-816e-bb1b196893be",
        "plantName": "Condorvine",
        "scientificName": "Marsdenia reichenbachii Triana",
        "family": "Asclepiadaceae",
        "wateringFrequency": "Seldom",
        "lightRequirement": "medium light",
        "temperatureRange": "cool",
        "soilType": "clay",
        "fertilizerFrequency": "Monthly",
        "bloomingSeason": "winter",
        "height": 66.67
    },
    {
        "id": "025df355-8154-412e-a24f-621622cb3710",
        "plantName": "Young's Snowbell",
        "scientificName": "Styrax platanifolius Engelm. ssp. youngiae (Cory) P.W. Fritsch",
        "family": "Styracaceae",
        "wateringFrequency": "Yearly",
        "lightRequirement": "medium light",
        "temperatureRange": "warm",
        "soilType": "clay",
        "fertilizerFrequency": "Never",
        "bloomingSeason": "spring",
        "height": 56.46
    },
    {
        "id": "45f439d6-7d49-49e9-a360-a0fc92b11009",
        "plantName": "Mountain Purple Pitcherplant",
        "scientificName": "Sarracenia purpurea L. ssp. purpurea var. montana D.E. Schnell & Determann",
        "family": "Sarraceniaceae",
        "wateringFrequency": "Monthly",
        "lightRequirement": "medium light",
        "temperatureRange": "moderate",
        "soilType": "sandy",
        "fertilizerFrequency": "Yearly",
        "bloomingSeason": "winter",
        "height": 10.88
    },
    {
        "id": "109dbbdf-0120-4f1f-bb64-a7d946eb01b2",
        "plantName": "Fall Sneezeweed",
        "scientificName": "Helenium autumnale L. var. grandiflorum (Nutt.) Torr. & A. Gray",
        "family": "Asteraceae",
        "wateringFrequency": "Weekly",
        "lightRequirement": "low light",
        "temperatureRange": "warm",
        "soilType": "loamy",
        "fertilizerFrequency": "Yearly",
        "bloomingSeason": "spring",
        "height": 42.24
    },
    {
        "id": "a738937c-b755-4fb8-9c1b-5cdf4b276e96",
        "plantName": "Skypilot",
        "scientificName": "Polemonium eximium Greene",
        "family": "Polemoniaceae",
        "wateringFrequency": "Seldom",
        "lightRequirement": "high light",
        "temperatureRange": "warm",
        "soilType": "clay",
        "fertilizerFrequency": "Never",
        "bloomingSeason": "winter",
        "height": 15.84
    },
    {
        "id": "900afb78-cd06-4905-b688-a15078ad3bfb",
        "plantName": "Clustered Fanpetals",
        "scientificName": "Sida glomerata Comm. ex Cav.",
        "family": "Malvaceae",
        "wateringFrequency": "Never",
        "lightRequirement": "medium light",
        "temperatureRange": "moderate",
        "soilType": "clay",
        "fertilizerFrequency": "Never",
        "bloomingSeason": "winter",
        "height": 79.53
    },
    {
        "id": "22f1ff32-6ea3-4162-aa85-6c7b77e22567",
        "plantName": "James' Seaheath",
        "scientificName": "Frankenia jamesii Torr. ex A. Gray",
        "family": "Frankeniaceae",
        "wateringFrequency": "Seldom",
        "lightRequirement": "high light",
        "temperatureRange": "warm",
        "soilType": "clay",
        "fertilizerFrequency": "Never",
        "bloomingSeason": "summer",
        "height": 10.66
    },
    {
        "id": "23603022-03dc-4787-9f96-e99590bfacf4",
        "plantName": "Fewflower Blazing Star",
        "scientificName": "Liatris pauciflora Pursh",
        "family": "Asteraceae",
        "wateringFrequency": "Never",
        "lightRequirement": "high light",
        "temperatureRange": "cool",
        "soilType": "loamy",
        "fertilizerFrequency": "Monthly",
        "bloomingSeason": "fall",
        "height": 97.65
    },
    {
        "id": "42f3c4f2-8d24-4a4a-9ff5-2cf3dcb4a0f6",
        "plantName": "Soft Popcornflower",
        "scientificName": "Plagiobothrys mollis (A. Gray) I.M. Johnst. var. mollis",
        "family": "Boraginaceae",
        "wateringFrequency": "Monthly",
        "lightRequirement": "high light",
        "temperatureRange": "cool",
        "soilType": "clay",
        "fertilizerFrequency": "Daily",
        "bloomingSeason": "winter",
        "height": 76.86
    },
    {
        "id": "ae4092b4-5467-4d01-890b-2bdae183b47b",
        "plantName": "Rugulose Shield Lichen",
        "scientificName": "Heterodermia rugulosa (Kurok.) Wetmore",
        "family": "Physciaceae",
        "wateringFrequency": "Daily",
        "lightRequirement": "low light",
        "temperatureRange": "cool",
        "soilType": "loamy",
        "fertilizerFrequency": "Often",
        "bloomingSeason": "winter",
        "height": 18.58
    },
    {
        "id": "3fa2a90f-3d03-4cda-9b0a-6f187afb25c7",
        "plantName": "Yellow Blanketflower",
        "scientificName": "Gaillardia flava Rydb.",
        "family": "Asteraceae",
        "wateringFrequency": "Seldom",
        "lightRequirement": "medium light",
        "temperatureRange": "warm",
        "soilType": "clay",
        "fertilizerFrequency": "Once",
        "bloomingSeason": "summer",
        "height": 18.92
    },
    {
        "id": "3042df22-5961-42cb-ab1d-5346f4238da7",
        "plantName": "Dactylospora Lichen",
        "scientificName": "Dactylospora attendenda (Nyl.) Arnold",
        "family": "Dactylosporaceae",
        "wateringFrequency": "Monthly",
        "lightRequirement": "medium light",
        "temperatureRange": "moderate",
        "soilType": "loamy",
        "fertilizerFrequency": "Weekly",
        "bloomingSeason": "fall",
        "height": 4.46
    },
    {
        "id": "3ff6c0b9-ae32-4d99-acd4-b2b08d09ef3a",
        "plantName": "Guava",
        "scientificName": "Psidium L.",
        "family": "Myrtaceae",
        "wateringFrequency": "Daily",
        "lightRequirement": "low light",
        "temperatureRange": "cool",
        "soilType": "clay",
        "fertilizerFrequency": "Yearly",
        "bloomingSeason": "winter",
        "height": 92.59
    },
    {
        "id": "44e08a4d-2a12-4666-ad29-45239e9f47a2",
        "plantName": "Xanthoparmelia Lichen",
        "scientificName": "Xanthoparmelia norhypopsila Hale",
        "family": "Parmeliaceae",
        "wateringFrequency": "Monthly",
        "lightRequirement": "high light",
        "temperatureRange": "moderate",
        "soilType": "loamy",
        "fertilizerFrequency": "Monthly",
        "bloomingSeason": "fall",
        "height": 60.59
    },
    {
        "id": "bbe3409c-1859-4dab-b3d0-d02d72118185",
        "plantName": "Blackmat Splashzone Moss",
        "scientificName": "Scouleria aquatica Hook.",
        "family": "Scouleriaceae",
        "wateringFrequency": "Often",
        "lightRequirement": "high light",
        "temperatureRange": "cool",
        "soilType": "sandy",
        "fertilizerFrequency": "Monthly",
        "bloomingSeason": "summer",
        "height": 74.91
    },
    {
        "id": "08448668-4be7-420f-81ce-b84811fc7c33",
        "plantName": "Pop Saltbush",
        "scientificName": "Atriplex spongiosa F. Muell.",
        "family": "Chenopodiaceae",
        "wateringFrequency": "Daily",
        "lightRequirement": "medium light",
        "temperatureRange": "warm",
        "soilType": "clay",
        "fertilizerFrequency": "Yearly",
        "bloomingSeason": "spring",
        "height": 13.73
    },
    {
        "id": "b69c72fe-666d-4ac6-a22b-b14bff79d3b7",
        "plantName": "Greenwood's Goldenbush",
        "scientificName": "Ericameria lignumviridis (S.L. Welsh) G.L. Nesom",
        "family": "Asteraceae",
        "wateringFrequency": "Daily",
        "lightRequirement": "low light",
        "temperatureRange": "moderate",
        "soilType": "loamy",
        "fertilizerFrequency": "Seldom",
        "bloomingSeason": "fall",
        "height": 22.07
    },
    {
        "id": "1ac633a8-5175-418b-9bdb-eb7a45672aef",
        "plantName": "Parry's Sedge",
        "scientificName": "Carex parryana Dewey var. brevisquama F.J. Herm.",
        "family": "Cyperaceae",
        "wateringFrequency": "Never",
        "lightRequirement": "medium light",
        "temperatureRange": "moderate",
        "soilType": "sandy",
        "fertilizerFrequency": "Never",
        "bloomingSeason": "summer",
        "height": 89.36
    },
    {
        "id": "c74af48f-5523-4dc6-8e61-2fc1dd86024f",
        "plantName": "Lavender Oldfield Aster",
        "scientificName": "Symphyotrichum priceae (Britton) G.L. Nesom",
        "family": "Asteraceae",
        "wateringFrequency": "Often",
        "lightRequirement": "medium light",
        "temperatureRange": "warm",
        "soilType": "sandy",
        "fertilizerFrequency": "Once",
        "bloomingSeason": "winter",
        "height": 30.33
    },
    {
        "id": "0aca2698-59e1-4912-b345-9ff78355212c",
        "plantName": "Candle Cholla",
        "scientificName": "Cylindropuntia kleiniae (DC.) F.M. Knuth",
        "family": "Cactaceae",
        "wateringFrequency": "Seldom",
        "lightRequirement": "high light",
        "temperatureRange": "warm",
        "soilType": "sandy",
        "fertilizerFrequency": "Weekly",
        "bloomingSeason": "spring",
        "height": 57.81
    },
    {
        "id": "91eb1c70-e1b8-49c5-820f-d744e78e2248",
        "plantName": "Kentucky Yellowwood",
        "scientificName": "Cladrastis kentukea (Dum. Cours.) Rudd",
        "family": "Fabaceae",
        "wateringFrequency": "Daily",
        "lightRequirement": "low light",
        "temperatureRange": "warm",
        "soilType": "clay",
        "fertilizerFrequency": "Often",
        "bloomingSeason": "summer",
        "height": 68.74
    },
    {
        "id": "34584c66-5da3-4af9-85d9-0dfc56fcfebc",
        "plantName": "Juniper Sedge",
        "scientificName": "Carex juniperorum Catling, Reznicek & Crins",
        "family": "Cyperaceae",
        "wateringFrequency": "Weekly",
        "lightRequirement": "low light",
        "temperatureRange": "moderate",
        "soilType": "loamy",
        "fertilizerFrequency": "Never",
        "bloomingSeason": "spring",
        "height": 93.38
    },
    {
        "id": "80ae67a9-0e64-4663-90c9-20c5b3a26afe",
        "plantName": "Candle Snuffer Moss",
        "scientificName": "Encalypta brevipes Schljak.",
        "family": "Encalyptaceae",
        "wateringFrequency": "Once",
        "lightRequirement": "medium light",
        "temperatureRange": "warm",
        "soilType": "loamy",
        "fertilizerFrequency": "Monthly",
        "bloomingSeason": "spring",
        "height": 10.31
    },
    {
        "id": "da30914f-bfb3-49e5-b843-60747966841b",
        "plantName": "Hyssopleaf Thoroughwort",
        "scientificName": "Eupatorium hyssopifolium L. var. calcaratum Fernald & B.G. Schub.",
        "family": "Asteraceae",
        "wateringFrequency": "Yearly",
        "lightRequirement": "low light",
        "temperatureRange": "warm",
        "soilType": "loamy",
        "fertilizerFrequency": "Monthly",
        "bloomingSeason": "winter",
        "height": 89.88
    },
    {
        "id": "1b859d28-a2ce-4ae3-9fd2-73cb420f4c45",
        "plantName": "Northwestern Thelypody",
        "scientificName": "Thelypodium paniculatum A. Nelson",
        "family": "Brassicaceae",
        "wateringFrequency": "Weekly",
        "lightRequirement": "high light",
        "temperatureRange": "warm",
        "soilType": "sandy",
        "fertilizerFrequency": "Monthly",
        "bloomingSeason": "summer",
        "height": 97.32
    },
    {
        "id": "9b3b11da-20d9-44af-a88d-edd3ca550cf9",
        "plantName": "Asterothyrium Lichen",
        "scientificName": "Asterothyrium Müll. Arg.",
        "family": "Thelotremataceae",
        "wateringFrequency": "Daily",
        "lightRequirement": "high light",
        "temperatureRange": "moderate",
        "soilType": "sandy",
        "fertilizerFrequency": "Yearly",
        "bloomingSeason": "summer",
        "height": 58.31
    },
    {
        "id": "28e151c3-e3e3-430f-9042-525dcfa595de",
        "plantName": "Cohoba Tree",
        "scientificName": "Anadenanthera peregrina (L.) Speg.",
        "family": "Fabaceae",
        "wateringFrequency": "Often",
        "lightRequirement": "high light",
        "temperatureRange": "cool",
        "soilType": "sandy",
        "fertilizerFrequency": "Monthly",
        "bloomingSeason": "summer",
        "height": 5.77
    },
    {
        "id": "3a9102ba-241e-477f-8d01-160be5283291",
        "plantName": "Honeyvine",
        "scientificName": "Cynanchum laeve (Michx.) Pers.",
        "family": "Asclepiadaceae",
        "wateringFrequency": "Weekly",
        "lightRequirement": "low light",
        "temperatureRange": "moderate",
        "soilType": "sandy",
        "fertilizerFrequency": "Monthly",
        "bloomingSeason": "spring",
        "height": 40.45
    },
    {
        "id": "45a2f920-6841-4eaf-9a2f-9c563835eeaf",
        "plantName": "Selkirk's Violet",
        "scientificName": "Viola selkirkii Pursh ex Goldie",
        "family": "Violaceae",
        "wateringFrequency": "Once",
        "lightRequirement": "high light",
        "temperatureRange": "cool",
        "soilType": "sandy",
        "fertilizerFrequency": "Seldom",
        "bloomingSeason": "summer",
        "height": 16.4
    },
    {
        "id": "3bda9d9c-bf56-45f5-91ac-38aaaf72532c",
        "plantName": "Hualalai Bur Cucumber",
        "scientificName": "Sicyos lasiocephalus Skottsb.",
        "family": "Cucurbitaceae",
        "wateringFrequency": "Once",
        "lightRequirement": "high light",
        "temperatureRange": "warm",
        "soilType": "sandy",
        "fertilizerFrequency": "Monthly",
        "bloomingSeason": "winter",
        "height": 35.8
    },
    {
        "id": "8b628074-1ed6-42ae-bdf3-e32890bcf154",
        "plantName": "Malaysian Aralia",
        "scientificName": "Polyscias cumingiana (C. Presl) Fernald-Vill.",
        "family": "Araliaceae",
        "wateringFrequency": "Monthly",
        "lightRequirement": "low light",
        "temperatureRange": "cool",
        "soilType": "clay",
        "fertilizerFrequency": "Yearly",
        "bloomingSeason": "spring",
        "height": 24.38
    },
    {
        "id": "a86f34b7-f866-4f0e-a339-383b3b4eed90",
        "plantName": "Zollinger's Indigo",
        "scientificName": "Indigofera zollingeriana Miq.",
        "family": "Fabaceae",
        "wateringFrequency": "Weekly",
        "lightRequirement": "high light",
        "temperatureRange": "moderate",
        "soilType": "sandy",
        "fertilizerFrequency": "Weekly",
        "bloomingSeason": "spring",
        "height": 45.65
    },
    {
        "id": "54e3566d-e9fd-4fe9-b91d-2847d9d6cbe2",
        "plantName": "White Doll's Daisy",
        "scientificName": "Boltonia asteroides (L.) L'Hér.",
        "family": "Asteraceae",
        "wateringFrequency": "Yearly",
        "lightRequirement": "low light",
        "temperatureRange": "warm",
        "soilType": "sandy",
        "fertilizerFrequency": "Never",
        "bloomingSeason": "fall",
        "height": 58.78
    },
    {
        "id": "218159bf-4f56-4a0f-a9e3-cd2ebe5e8295",
        "plantName": "Foxtail Pine",
        "scientificName": "Pinus balfouriana Balf. ssp. austrina R.J. Mastrog & J.D. Mastrog.",
        "family": "Pinaceae",
        "wateringFrequency": "Weekly",
        "lightRequirement": "high light",
        "temperatureRange": "cool",
        "soilType": "sandy",
        "fertilizerFrequency": "Never",
        "bloomingSeason": "winter",
        "height": 68.56
    },
    {
        "id": "7faf1a08-a639-4d84-9f14-bb8b225d7953",
        "plantName": "White Thatch Palm",
        "scientificName": "Leucothrinax C.Lewis & Zona",
        "family": "Arecaceae",
        "wateringFrequency": "Once",
        "lightRequirement": "low light",
        "temperatureRange": "warm",
        "soilType": "loamy",
        "fertilizerFrequency": "Never",
        "bloomingSeason": "fall",
        "height": 43.15
    },
    {
        "id": "0092d989-bdc0-4d9a-9c15-5b1abc9ec20f",
        "plantName": "Snow Lichen",
        "scientificName": "Stereocaulon leprocephalum Vain.",
        "family": "Stereocaulaceae",
        "wateringFrequency": "Monthly",
        "lightRequirement": "medium light",
        "temperatureRange": "cool",
        "soilType": "sandy",
        "fertilizerFrequency": "Never",
        "bloomingSeason": "fall",
        "height": 21.25
    },
    {
        "id": "06c70c4e-30db-4cde-9abf-df534130e79b",
        "plantName": "Greenvein Lady's Tresses",
        "scientificName": "Spiranthes praecox (Walter) S. Watson",
        "family": "Orchidaceae",
        "wateringFrequency": "Seldom",
        "lightRequirement": "high light",
        "temperatureRange": "warm",
        "soilType": "sandy",
        "fertilizerFrequency": "Daily",
        "bloomingSeason": "summer",
        "height": 88.87
    },
    {
        "id": "15836cde-7265-4d0f-9d8e-3b6127687d2e",
        "plantName": "Petty Spurge",
        "scientificName": "Euphorbia peplus L.",
        "family": "Euphorbiaceae",
        "wateringFrequency": "Yearly",
        "lightRequirement": "medium light",
        "temperatureRange": "moderate",
        "soilType": "sandy",
        "fertilizerFrequency": "Seldom",
        "bloomingSeason": "spring",
        "height": 42.58
    },
    {
        "id": "9df44962-5c6e-4a47-9566-63b6d7d2ae47",
        "plantName": "Waihee Clermontia",
        "scientificName": "Clermontia multiflora Hillebr.",
        "family": "Campanulaceae",
        "wateringFrequency": "Often",
        "lightRequirement": "low light",
        "temperatureRange": "moderate",
        "soilType": "sandy",
        "fertilizerFrequency": "Often",
        "bloomingSeason": "fall",
        "height": 26.84
    },
    {
        "id": "da246710-fe44-4f1e-a6d9-730410b5a143",
        "plantName": "Stiff Goldenrod",
        "scientificName": "Oligoneuron rigidum (L.) Small var. rigidum",
        "family": "Asteraceae",
        "wateringFrequency": "Never",
        "lightRequirement": "medium light",
        "temperatureRange": "cool",
        "soilType": "sandy",
        "fertilizerFrequency": "Monthly",
        "bloomingSeason": "winter",
        "height": 45.09
    },
    {
        "id": "f2fba8fd-2cb5-4466-8ffd-acd81f1c6fbf",
        "plantName": "White Fringed Orchid",
        "scientificName": "Platanthera blephariglottis (Willd.) Lindl. var. conspicua (Nash) Luer",
        "family": "Orchidaceae",
        "wateringFrequency": "Monthly",
        "lightRequirement": "low light",
        "temperatureRange": "warm",
        "soilType": "loamy",
        "fertilizerFrequency": "Never",
        "bloomingSeason": "fall",
        "height": 24.37
    },
    {
        "id": "5e7b0b2e-5899-4322-965a-6ee5aa7fdf59",
        "plantName": "Smallflower Fumewort",
        "scientificName": "Corydalis micrantha (Engelm. ex A. Gray) A. Gray",
        "family": "Fumariaceae",
        "wateringFrequency": "Once",
        "lightRequirement": "low light",
        "temperatureRange": "moderate",
        "soilType": "loamy",
        "fertilizerFrequency": "Never",
        "bloomingSeason": "spring",
        "height": 17.1
    },
    {
        "id": "41394fdc-ad28-44c1-98d5-bb6204f10ce8",
        "plantName": "Sphinctrina Lichen",
        "scientificName": "Sphinctrina turbinata (Pers. ex Fr.) De Not.",
        "family": "Sphinctrinaceae",
        "wateringFrequency": "Once",
        "lightRequirement": "medium light",
        "temperatureRange": "moderate",
        "soilType": "loamy",
        "fertilizerFrequency": "Often",
        "bloomingSeason": "winter",
        "height": 38.23
    },
    {
        "id": "ce7bcb09-5cbb-4672-ac42-b904c3611c02",
        "plantName": "Solidstem Burnet Saxifrage",
        "scientificName": "Pimpinella saxifraga L. ssp. saxifraga",
        "family": "Apiaceae",
        "wateringFrequency": "Weekly",
        "lightRequirement": "medium light",
        "temperatureRange": "warm",
        "soilType": "clay",
        "fertilizerFrequency": "Daily",
        "bloomingSeason": "winter",
        "height": 57.91
    },
    {
        "id": "1f93e770-1525-4b62-bbc7-edb2200d115a",
        "plantName": "Micromitrium Moss",
        "scientificName": "Micromitrium Austin",
        "family": "Ephemeraceae",
        "wateringFrequency": "Weekly",
        "lightRequirement": "medium light",
        "temperatureRange": "moderate",
        "soilType": "sandy",
        "fertilizerFrequency": "Daily",
        "bloomingSeason": "winter",
        "height": 52.63
    },
    {
        "id": "73970686-a85b-4cf8-b730-b49693721ade",
        "plantName": "Bloom Peak Dwarf-primrose",
        "scientificName": "Douglasia conservatorum Björk",
        "family": "Primulaceae",
        "wateringFrequency": "Daily",
        "lightRequirement": "low light",
        "temperatureRange": "cool",
        "soilType": "clay",
        "fertilizerFrequency": "Often",
        "bloomingSeason": "winter",
        "height": 81.36
    },
    {
        "id": "6a242d7e-05ba-4a8d-8d65-2355c61c3e79",
        "plantName": "Smooth Winterberry",
        "scientificName": "Ilex laevigata (Pursh) A. Gray",
        "family": "Aquifoliaceae",
        "wateringFrequency": "Yearly",
        "lightRequirement": "high light",
        "temperatureRange": "cool",
        "soilType": "clay",
        "fertilizerFrequency": "Often",
        "bloomingSeason": "summer",
        "height": 89.87
    },
    {
        "id": "e91dce30-bd5f-47ff-a424-f24ae8e39309",
        "plantName": "Looseflower Water-willow",
        "scientificName": "Justicia ovata (Walter) Lindau var. ovata",
        "family": "Acanthaceae",
        "wateringFrequency": "Yearly",
        "lightRequirement": "low light",
        "temperatureRange": "warm",
        "soilType": "sandy",
        "fertilizerFrequency": "Often",
        "bloomingSeason": "fall",
        "height": 3.19
    },
    {
        "id": "067af988-557d-4367-89c3-f45f92992b3d",
        "plantName": "Rusby's Blazingstar",
        "scientificName": "Mentzelia rusbyi Wooton",
        "family": "Loasaceae",
        "wateringFrequency": "Seldom",
        "lightRequirement": "low light",
        "temperatureRange": "cool",
        "soilType": "sandy",
        "fertilizerFrequency": "Once",
        "bloomingSeason": "winter",
        "height": 47.59
    },
    {
        "id": "1adf22bd-c2e0-4a59-ada6-298e3863b2cb",
        "plantName": "Bearded Prairie Clover",
        "scientificName": "Dalea pogonathera A. Gray var. pogonathera",
        "family": "Fabaceae",
        "wateringFrequency": "Weekly",
        "lightRequirement": "high light",
        "temperatureRange": "warm",
        "soilType": "sandy",
        "fertilizerFrequency": "Never",
        "bloomingSeason": "fall",
        "height": 46.18
    },
    {
        "id": "b5d97075-fbe7-414c-905b-4939e30c410b",
        "plantName": "Bigelow's Monkeyflower",
        "scientificName": "Mimulus bigelovii (A. Gray) A. Gray var. bigelovii",
        "family": "Scrophulariaceae",
        "wateringFrequency": "Once",
        "lightRequirement": "medium light",
        "temperatureRange": "moderate",
        "soilType": "clay",
        "fertilizerFrequency": "Seldom",
        "bloomingSeason": "winter",
        "height": 99.75
    },
    {
        "id": "997cc127-fcfc-4e9d-9d29-e777d20df5f9",
        "plantName": "Tuber Anemone",
        "scientificName": "Anemone tuberosa Rydb. var. tuberosa",
        "family": "Ranunculaceae",
        "wateringFrequency": "Never",
        "lightRequirement": "low light",
        "temperatureRange": "moderate",
        "soilType": "sandy",
        "fertilizerFrequency": "Never",
        "bloomingSeason": "spring",
        "height": 95.99
    },
    {
        "id": "cc4599e4-1f95-48ad-a789-c5e691bb8401",
        "plantName": "Desert Madwort",
        "scientificName": "Alyssum desertorum Stapf var. desertorum",
        "family": "Brassicaceae",
        "wateringFrequency": "Monthly",
        "lightRequirement": "high light",
        "temperatureRange": "warm",
        "soilType": "loamy",
        "fertilizerFrequency": "Daily",
        "bloomingSeason": "winter",
        "height": 41.69
    },
    {
        "id": "e6826ebf-7508-4033-993b-e34975353dd1",
        "plantName": "Western Meadow-rue",
        "scientificName": "Thalictrum occidentale A. Gray var. macounii B. Boivin",
        "family": "Ranunculaceae",
        "wateringFrequency": "Weekly",
        "lightRequirement": "high light",
        "temperatureRange": "warm",
        "soilType": "loamy",
        "fertilizerFrequency": "Monthly",
        "bloomingSeason": "spring",
        "height": 65.54
    },
    {
        "id": "42ef77db-7597-492d-8012-d40705649072",
        "plantName": "Cochineal Nopal Cactus",
        "scientificName": "Opuntia cochenillifera (L.) Mill.",
        "family": "Cactaceae",
        "wateringFrequency": "Often",
        "lightRequirement": "high light",
        "temperatureRange": "warm",
        "soilType": "loamy",
        "fertilizerFrequency": "Monthly",
        "bloomingSeason": "fall",
        "height": 82.89
    },
    {
        "id": "d4e55114-fba5-411e-9f1e-0cbe14d9a811",
        "plantName": "Ahti's Neofuscelia Lichen",
        "scientificName": "Neofuscelia ahtii (Essl.) Essl.",
        "family": "Parmeliaceae",
        "wateringFrequency": "Weekly",
        "lightRequirement": "medium light",
        "temperatureRange": "cool",
        "soilType": "clay",
        "fertilizerFrequency": "Seldom",
        "bloomingSeason": "winter",
        "height": 19.23
    },
    {
        "id": "6745e78d-ad02-4a01-b156-a00e60d09c79",
        "plantName": "Dwarf Mountain Ragwort",
        "scientificName": "Senecio fremontii Torr. & A. Gray",
        "family": "Asteraceae",
        "wateringFrequency": "Seldom",
        "lightRequirement": "high light",
        "temperatureRange": "moderate",
        "soilType": "sandy",
        "fertilizerFrequency": "Never",
        "bloomingSeason": "spring",
        "height": 43.47
    },
    {
        "id": "d0854d5d-89f8-40f0-9645-a40aabe9c64d",
        "plantName": "Aongstroemia Moss",
        "scientificName": "Aongstroemia Bruch & Schimp.",
        "family": "Dicranaceae",
        "wateringFrequency": "Weekly",
        "lightRequirement": "high light",
        "temperatureRange": "moderate",
        "soilType": "clay",
        "fertilizerFrequency": "Weekly",
        "bloomingSeason": "fall",
        "height": 58.28
    },
    {
        "id": "afce7767-51e0-49a6-9744-b07240fe4e2e",
        "plantName": "Indian Tobacco",
        "scientificName": "Nicotiana quadrivalvis Pursh var. quadrivalvis",
        "family": "Solanaceae",
        "wateringFrequency": "Never",
        "lightRequirement": "low light",
        "temperatureRange": "moderate",
        "soilType": "clay",
        "fertilizerFrequency": "Yearly",
        "bloomingSeason": "spring",
        "height": 55.71
    },
    {
        "id": "65e46291-07ce-4c08-8e15-4200f7a3664b",
        "plantName": "Hornwort",
        "scientificName": "Anthoceros adscendens Lehm. & Lindenb.",
        "family": "Anthocerotaceae",
        "wateringFrequency": "Daily",
        "lightRequirement": "high light",
        "temperatureRange": "moderate",
        "soilType": "loamy",
        "fertilizerFrequency": "Daily",
        "bloomingSeason": "summer",
        "height": 55.5
    },
    {
        "id": "25be8f13-fb43-40b8-996e-4270a9f67074",
        "plantName": "Jumping Cholla",
        "scientificName": "Cylindropuntia fulgida (Engelm.) F.M. Knuth",
        "family": "Cactaceae",
        "wateringFrequency": "Yearly",
        "lightRequirement": "medium light",
        "temperatureRange": "warm",
        "soilType": "clay",
        "fertilizerFrequency": "Monthly",
        "bloomingSeason": "fall",
        "height": 71.12
    },
    {
        "id": "a4f19105-0e27-443e-bcc6-4924b4315ae2",
        "plantName": "Balsamroot",
        "scientificName": "Balsamorhiza ×tomentosa Rydb. (pro sp.)",
        "family": "Asteraceae",
        "wateringFrequency": "Weekly",
        "lightRequirement": "high light",
        "temperatureRange": "moderate",
        "soilType": "sandy",
        "fertilizerFrequency": "Daily",
        "bloomingSeason": "summer",
        "height": 43.79
    },
    {
        "id": "73073518-3781-4366-9b84-7580443c261e",
        "plantName": "Annual Clary",
        "scientificName": "Salvia viridis L.",
        "family": "Lamiaceae",
        "wateringFrequency": "Weekly",
        "lightRequirement": "high light",
        "temperatureRange": "cool",
        "soilType": "loamy",
        "fertilizerFrequency": "Never",
        "bloomingSeason": "summer",
        "height": 79.53
    },
    {
        "id": "424081a9-9555-44a9-a220-66ea5accc966",
        "plantName": "Sawtooth Lewisia",
        "scientificName": "Lewisia serrata Heckard & Stebbins",
        "family": "Portulacaceae",
        "wateringFrequency": "Daily",
        "lightRequirement": "low light",
        "temperatureRange": "moderate",
        "soilType": "clay",
        "fertilizerFrequency": "Seldom",
        "bloomingSeason": "summer",
        "height": 99.92
    },
    {
        "id": "57c20f82-fa14-4772-9c91-88ade21a1cb0",
        "plantName": "Sunset Crater Beardtongue",
        "scientificName": "Penstemon clutei A. Nelson",
        "family": "Scrophulariaceae",
        "wateringFrequency": "Daily",
        "lightRequirement": "low light",
        "temperatureRange": "moderate",
        "soilType": "clay",
        "fertilizerFrequency": "Weekly",
        "bloomingSeason": "fall",
        "height": 59.51
    },
    {
        "id": "7c8bfc9e-63ff-4423-8da5-1b2cadf03329",
        "plantName": "Schimper's Ditrichum Moss",
        "scientificName": "Ditrichum schimperi (Lesq.) Kuntze",
        "family": "Ditrichaceae",
        "wateringFrequency": "Weekly",
        "lightRequirement": "high light",
        "temperatureRange": "warm",
        "soilType": "sandy",
        "fertilizerFrequency": "Never",
        "bloomingSeason": "spring",
        "height": 89.86
    },
    {
        "id": "79399453-ec84-4a4b-a22b-44846b0c69f3",
        "plantName": "Vanilla-scented Bog Orchid",
        "scientificName": "Pseudorchis straminea (Fernald) Soó",
        "family": "Orchidaceae",
        "wateringFrequency": "Daily",
        "lightRequirement": "high light",
        "temperatureRange": "warm",
        "soilType": "clay",
        "fertilizerFrequency": "Never",
        "bloomingSeason": "winter",
        "height": 32.77
    },
    {
        "id": "f6c07ecd-c62d-4451-a332-79282ad86bdd",
        "plantName": "Low Woodland Sedge",
        "scientificName": "Carex socialis Mohlenbr. & Schwegm.",
        "family": "Cyperaceae",
        "wateringFrequency": "Weekly",
        "lightRequirement": "high light",
        "temperatureRange": "warm",
        "soilType": "clay",
        "fertilizerFrequency": "Monthly",
        "bloomingSeason": "summer",
        "height": 1.32
    },
    {
        "id": "a65f1649-90df-4419-b596-6063b9fd4240",
        "plantName": "California Ponysfoot",
        "scientificName": "Dichondra donelliana Tharp & M.C. Johnst.",
        "family": "Convolvulaceae",
        "wateringFrequency": "Yearly",
        "lightRequirement": "medium light",
        "temperatureRange": "moderate",
        "soilType": "sandy",
        "fertilizerFrequency": "Never",
        "bloomingSeason": "spring",
        "height": 90.77
    },
    {
        "id": "910bfeb9-ca39-4c52-9034-dec0aecb1739",
        "plantName": "Wine Raspberry",
        "scientificName": "Rubus phoenicolasius Maxim.",
        "family": "Rosaceae",
        "wateringFrequency": "Yearly",
        "lightRequirement": "medium light",
        "temperatureRange": "warm",
        "soilType": "clay",
        "fertilizerFrequency": "Daily",
        "bloomingSeason": "summer",
        "height": 42.38
    },
    {
        "id": "2c82f5e9-fee8-410f-9b7f-7b3aaf79d41b",
        "plantName": "Rosy Buckwheat",
        "scientificName": "Eriogonum rosense A. Nelson & Kennedy var. rosense",
        "family": "Polygonaceae",
        "wateringFrequency": "Daily",
        "lightRequirement": "low light",
        "temperatureRange": "warm",
        "soilType": "clay",
        "fertilizerFrequency": "Weekly",
        "bloomingSeason": "summer",
        "height": 93.17
    },
    {
        "id": "22f11059-0ee4-4458-8602-76537d4aafa3",
        "plantName": "Capitan Mountains Alumroot",
        "scientificName": "Heuchera woodsiaphila P.J. Alexander",
        "family": "Saxifragaceae",
        "wateringFrequency": "Yearly",
        "lightRequirement": "medium light",
        "temperatureRange": "cool",
        "soilType": "loamy",
        "fertilizerFrequency": "Yearly",
        "bloomingSeason": "summer",
        "height": 25.42
    },
    {
        "id": "fec814f0-1425-447d-a23a-ef9eafe8afa2",
        "plantName": "Ophioparma Lichen",
        "scientificName": "Ophioparma Norman",
        "family": "Ophioparmaceae",
        "wateringFrequency": "Daily",
        "lightRequirement": "low light",
        "temperatureRange": "warm",
        "soilType": "clay",
        "fertilizerFrequency": "Daily",
        "bloomingSeason": "winter",
        "height": 22.07
    },
    {
        "id": "b021a21a-d478-4731-a843-8dae2a44529a",
        "plantName": "Olympic Mullein",
        "scientificName": "Verbascum olympicum Boiss.",
        "family": "Scrophulariaceae",
        "wateringFrequency": "Seldom",
        "lightRequirement": "medium light",
        "temperatureRange": "moderate",
        "soilType": "clay",
        "fertilizerFrequency": "Monthly",
        "bloomingSeason": "winter",
        "height": 90.68
    },
    {
        "id": "5dc59e68-7832-41dc-b540-e47ffb69d2b9",
        "plantName": "Plains Flatsedge",
        "scientificName": "Cyperus onerosus M.C. Johnst.",
        "family": "Cyperaceae",
        "wateringFrequency": "Once",
        "lightRequirement": "high light",
        "temperatureRange": "cool",
        "soilType": "clay",
        "fertilizerFrequency": "Daily",
        "bloomingSeason": "fall",
        "height": 31.05
    },
    {
        "id": "67ac44e2-cd7f-47bd-bed3-e0a0f5bd5019",
        "plantName": "Broadleaf Helleborine",
        "scientificName": "Epipactis helleborine (L.) Crantz",
        "family": "Orchidaceae",
        "wateringFrequency": "Never",
        "lightRequirement": "low light",
        "temperatureRange": "moderate",
        "soilType": "clay",
        "fertilizerFrequency": "Never",
        "bloomingSeason": "summer",
        "height": 51.91
    },
    {
        "id": "b70581d7-fbcf-433d-a63f-ab45d6ef530a",
        "plantName": "Hemionitis",
        "scientificName": "Hemionitis L.",
        "family": "Pteridaceae",
        "wateringFrequency": "Seldom",
        "lightRequirement": "low light",
        "temperatureRange": "warm",
        "soilType": "sandy",
        "fertilizerFrequency": "Seldom",
        "bloomingSeason": "winter",
        "height": 83.24
    },
    {
        "id": "5e6b1746-335d-42f8-b41c-539ab0f274c2",
        "plantName": "Pine Green Gentian",
        "scientificName": "Frasera neglecta H.M. Hall",
        "family": "Gentianaceae",
        "wateringFrequency": "Weekly",
        "lightRequirement": "medium light",
        "temperatureRange": "cool",
        "soilType": "loamy",
        "fertilizerFrequency": "Weekly",
        "bloomingSeason": "fall",
        "height": 11.88
    },
    {
        "id": "b97fec49-a3d8-45c6-b795-8f4ff1be5777",
        "plantName": "Glandweed",
        "scientificName": "Parentucellia Viv.",
        "family": "Scrophulariaceae",
        "wateringFrequency": "Once",
        "lightRequirement": "low light",
        "temperatureRange": "warm",
        "soilType": "loamy",
        "fertilizerFrequency": "Yearly",
        "bloomingSeason": "spring",
        "height": 62.97
    },
    {
        "id": "0795f48b-806b-44a4-a097-2237ce94c31b",
        "plantName": "Pacific Racomitrium Moss",
        "scientificName": "Racomitrium pacificum Irel. & Spence",
        "family": "Grimmiaceae",
        "wateringFrequency": "Seldom",
        "lightRequirement": "low light",
        "temperatureRange": "warm",
        "soilType": "sandy",
        "fertilizerFrequency": "Weekly",
        "bloomingSeason": "spring",
        "height": 49.76
    },
    {
        "id": "83418626-e628-40d9-a644-aa456a166823",
        "plantName": "Mt. Atlas Mastic Tree",
        "scientificName": "Pistacia atlantica Desf.",
        "family": "Anacardiaceae",
        "wateringFrequency": "Daily",
        "lightRequirement": "low light",
        "temperatureRange": "moderate",
        "soilType": "clay",
        "fertilizerFrequency": "Once",
        "bloomingSeason": "winter",
        "height": 26.06
    },
    {
        "id": "65719938-3262-4d87-9c2f-ecd816d511dc",
        "plantName": "Snail Medick",
        "scientificName": "Medicago scutellata (L.) Mill.",
        "family": "Fabaceae",
        "wateringFrequency": "Once",
        "lightRequirement": "low light",
        "temperatureRange": "moderate",
        "soilType": "clay",
        "fertilizerFrequency": "Weekly",
        "bloomingSeason": "fall",
        "height": 78.13
    },
    {
        "id": "d7485928-4c16-407a-9ba7-26759b452617",
        "plantName": "Trumpet Gooseberry",
        "scientificName": "Ribes leptanthum A. Gray",
        "family": "Grossulariaceae",
        "wateringFrequency": "Often",
        "lightRequirement": "low light",
        "temperatureRange": "cool",
        "soilType": "sandy",
        "fertilizerFrequency": "Often",
        "bloomingSeason": "summer",
        "height": 11.77
    },
    {
        "id": "d28cd643-ec20-4b6d-8155-803e36d75bcf",
        "plantName": "Sea Aster",
        "scientificName": "Tripolium pannonicum (Jacq.) Dobrocz.",
        "family": "Asteraceae",
        "wateringFrequency": "Monthly",
        "lightRequirement": "medium light",
        "temperatureRange": "cool",
        "soilType": "clay",
        "fertilizerFrequency": "Daily",
        "bloomingSeason": "fall",
        "height": 54.46
    },
    {
        "id": "41dd188b-d417-4a0f-9311-e9eac85f2e4d",
        "plantName": "Quackgrass",
        "scientificName": "Elymus repens (L.) Gould",
        "family": "Poaceae",
        "wateringFrequency": "Once",
        "lightRequirement": "low light",
        "temperatureRange": "moderate",
        "soilType": "loamy",
        "fertilizerFrequency": "Monthly",
        "bloomingSeason": "winter",
        "height": 8.49
    },
    {
        "id": "97ee736f-2adf-4914-a914-e9696d1e9c5c",
        "plantName": "Monterey Mariposa Lily",
        "scientificName": "Calochortus uniflorus Hook. & Arn.",
        "family": "Liliaceae",
        "wateringFrequency": "Yearly",
        "lightRequirement": "medium light",
        "temperatureRange": "warm",
        "soilType": "loamy",
        "fertilizerFrequency": "Never",
        "bloomingSeason": "fall",
        "height": 59.2
    },
    {
        "id": "0e714a38-bc1b-471e-9e11-b413d043766f",
        "plantName": "Cracked Lichen",
        "scientificName": "Acarospora asperata H. Magn.",
        "family": "Acarosporaceae",
        "wateringFrequency": "Never",
        "lightRequirement": "medium light",
        "temperatureRange": "cool",
        "soilType": "loamy",
        "fertilizerFrequency": "Daily",
        "bloomingSeason": "winter",
        "height": 46.37
    },
    {
        "id": "ad48b53e-0ebc-4076-ba05-0ca187a3e20e",
        "plantName": "Nepalese Browntop",
        "scientificName": "Microstegium vimineum (Trin.) A. Camus",
        "family": "Poaceae",
        "wateringFrequency": "Monthly",
        "lightRequirement": "low light",
        "temperatureRange": "moderate",
        "soilType": "sandy",
        "fertilizerFrequency": "Once",
        "bloomingSeason": "winter",
        "height": 4.22
    },
    {
        "id": "8cfbbe09-f08c-4dbd-b144-b1e4db8ef7d8",
        "plantName": "Fragrant Orchid",
        "scientificName": "Gymnadenia conopsea (L.) R. Br.",
        "family": "Orchidaceae",
        "wateringFrequency": "Monthly",
        "lightRequirement": "low light",
        "temperatureRange": "cool",
        "soilType": "clay",
        "fertilizerFrequency": "Once",
        "bloomingSeason": "summer",
        "height": 99.55
    },
    {
        "id": "9fe234b9-48af-4977-849f-03ed2187e2c2",
        "plantName": "Southernwood",
        "scientificName": "Artemisia abrotanum L.",
        "family": "Asteraceae",
        "wateringFrequency": "Once",
        "lightRequirement": "medium light",
        "temperatureRange": "moderate",
        "soilType": "loamy",
        "fertilizerFrequency": "Never",
        "bloomingSeason": "spring",
        "height": 98.78
    },
    {
        "id": "ab4712cc-d600-4918-8584-eb0c23557c3a",
        "plantName": "Texas Pricklyleaf",
        "scientificName": "Thymophylla setifolia Lag.",
        "family": "Asteraceae",
        "wateringFrequency": "Weekly",
        "lightRequirement": "high light",
        "temperatureRange": "warm",
        "soilType": "clay",
        "fertilizerFrequency": "Never",
        "bloomingSeason": "winter",
        "height": 17.79
    },
    {
        "id": "f52b7048-0e6e-4daf-99f5-7417354d4dd0",
        "plantName": "Floating Primrose-willow",
        "scientificName": "Ludwigia peploides (Kunth) P.H. Raven ssp. glabrescens (Kuntze) P.H. Raven",
        "family": "Onagraceae",
        "wateringFrequency": "Weekly",
        "lightRequirement": "high light",
        "temperatureRange": "warm",
        "soilType": "clay",
        "fertilizerFrequency": "Seldom",
        "bloomingSeason": "winter",
        "height": 62.29
    },
    {
        "id": "e3fdbf2a-a1c1-4bb1-82e6-23a299cd90fa",
        "plantName": "Simpson's Primrose-willow",
        "scientificName": "Ludwigia simpsonii Chapm.",
        "family": "Onagraceae",
        "wateringFrequency": "Weekly",
        "lightRequirement": "high light",
        "temperatureRange": "moderate",
        "soilType": "loamy",
        "fertilizerFrequency": "Weekly",
        "bloomingSeason": "summer",
        "height": 77.06
    },
    {
        "id": "8a5bb42a-4fdf-4bae-99c3-06664f396252",
        "plantName": "Eleutherine",
        "scientificName": "Eleutherine Herb.",
        "family": "Iridaceae",
        "wateringFrequency": "Weekly",
        "lightRequirement": "medium light",
        "temperatureRange": "moderate",
        "soilType": "clay",
        "fertilizerFrequency": "Never",
        "bloomingSeason": "winter",
        "height": 20.04
    },
    {
        "id": "b99421ea-23dd-44fa-a624-c1fe81b037a9",
        "plantName": "Tweedy's Fleabane",
        "scientificName": "Erigeron tweedyi Canby",
        "family": "Asteraceae",
        "wateringFrequency": "Yearly",
        "lightRequirement": "low light",
        "temperatureRange": "moderate",
        "soilType": "clay",
        "fertilizerFrequency": "Yearly",
        "bloomingSeason": "spring",
        "height": 40.93
    },
    {
        "id": "8cb33672-e7bb-4c39-8dc2-9c22168e2e2e",
        "plantName": "American Lotus",
        "scientificName": "Nelumbo lutea Willd.",
        "family": "Nelumbonaceae",
        "wateringFrequency": "Weekly",
        "lightRequirement": "medium light",
        "temperatureRange": "warm",
        "soilType": "sandy",
        "fertilizerFrequency": "Never",
        "bloomingSeason": "spring",
        "height": 41.27
    },
    {
        "id": "ad7727ef-1ba1-468c-bd08-8e70a803c6eb",
        "plantName": "Palo Iloron",
        "scientificName": "Antirhea lucida (Sw.) Hook. f.",
        "family": "Rubiaceae",
        "wateringFrequency": "Often",
        "lightRequirement": "medium light",
        "temperatureRange": "warm",
        "soilType": "loamy",
        "fertilizerFrequency": "Daily",
        "bloomingSeason": "summer",
        "height": 51.22
    },
    {
        "id": "8e0c774f-b303-4173-928c-c394f68604fd",
        "plantName": "Rough Dubautia",
        "scientificName": "Dubautia scabra (DC.) D.D. Keck ssp. scabra",
        "family": "Asteraceae",
        "wateringFrequency": "Yearly",
        "lightRequirement": "high light",
        "temperatureRange": "moderate",
        "soilType": "sandy",
        "fertilizerFrequency": "Daily",
        "bloomingSeason": "fall",
        "height": 70.56
    },
    {
        "id": "884a2e63-23d5-48a2-b4b1-9d5bccdba717",
        "plantName": "Desert Muhly",
        "scientificName": "Muhlenbergia glauca (Nees) B.D. Jacks.",
        "family": "Poaceae",
        "wateringFrequency": "Monthly",
        "lightRequirement": "medium light",
        "temperatureRange": "cool",
        "soilType": "loamy",
        "fertilizerFrequency": "Monthly",
        "bloomingSeason": "spring",
        "height": 40.53
    },
    {
        "id": "0e7b8b32-335d-4199-b51b-2b8c0f2d8e8b",
        "plantName": "Resindot Sunflower",
        "scientificName": "Helianthus resinosus Small",
        "family": "Asteraceae",
        "wateringFrequency": "Seldom",
        "lightRequirement": "medium light",
        "temperatureRange": "cool",
        "soilType": "clay",
        "fertilizerFrequency": "Weekly",
        "bloomingSeason": "summer",
        "height": 79.95
    },
    {
        "id": "711c8212-fe95-474e-a376-a86dd1d4bdbb",
        "plantName": "Dicranoweisia Moss",
        "scientificName": "Dicranoweisia Lindb. ex Milde",
        "family": "Dicranaceae",
        "wateringFrequency": "Never",
        "lightRequirement": "low light",
        "temperatureRange": "moderate",
        "soilType": "loamy",
        "fertilizerFrequency": "Once",
        "bloomingSeason": "fall",
        "height": 23.96
    },
    {
        "id": "7c4ae102-798e-489c-a8f8-70e290b56089",
        "plantName": "Currant",
        "scientificName": "Ribes spicatum E. Robson",
        "family": "Grossulariaceae",
        "wateringFrequency": "Often",
        "lightRequirement": "high light",
        "temperatureRange": "moderate",
        "soilType": "sandy",
        "fertilizerFrequency": "Daily",
        "bloomingSeason": "winter",
        "height": 26.08
    },
    {
        "id": "0afb9bb1-a546-417c-920a-2df4f2dd5aa1",
        "plantName": "Vega Blanca",
        "scientificName": "Brunfelsia lactea Krug & Urb.",
        "family": "Solanaceae",
        "wateringFrequency": "Once",
        "lightRequirement": "high light",
        "temperatureRange": "moderate",
        "soilType": "sandy",
        "fertilizerFrequency": "Weekly",
        "bloomingSeason": "summer",
        "height": 71.23
    },
    {
        "id": "36f985f1-406d-42fc-a5ce-52c2251ea120",
        "plantName": "Washerwoman",
        "scientificName": "Alternanthera caracasana Kunth",
        "family": "Amaranthaceae",
        "wateringFrequency": "Seldom",
        "lightRequirement": "high light",
        "temperatureRange": "moderate",
        "soilType": "loamy",
        "fertilizerFrequency": "Never",
        "bloomingSeason": "spring",
        "height": 7.41
    },
    {
        "id": "20cc6a62-2d24-4c1a-aea8-471d2055962c",
        "plantName": "Mock Leopardbane",
        "scientificName": "Arnica dealbata (A. Gray) B.G. Baldw.",
        "family": "Asteraceae",
        "wateringFrequency": "Daily",
        "lightRequirement": "medium light",
        "temperatureRange": "moderate",
        "soilType": "clay",
        "fertilizerFrequency": "Often",
        "bloomingSeason": "winter",
        "height": 71.97
    },
    {
        "id": "17c09cad-a4a5-4724-ac6a-0bd5882bc08d",
        "plantName": "Threepetal Bedstraw",
        "scientificName": "Galium trifidum L. ssp. halophilum (Fernald & Wiegand) Puff",
        "family": "Rubiaceae",
        "wateringFrequency": "Once",
        "lightRequirement": "medium light",
        "temperatureRange": "moderate",
        "soilType": "clay",
        "fertilizerFrequency": "Seldom",
        "bloomingSeason": "summer",
        "height": 25.42
    },
    {
        "id": "3b0ce536-c34d-43ce-9623-d68c0266c773",
        "plantName": "Berlandier's Lobelia",
        "scientificName": "Lobelia berlandieri A. DC.",
        "family": "Campanulaceae",
        "wateringFrequency": "Monthly",
        "lightRequirement": "high light",
        "temperatureRange": "cool",
        "soilType": "sandy",
        "fertilizerFrequency": "Seldom",
        "bloomingSeason": "winter",
        "height": 85.82
    },
    {
        "id": "89075722-c172-4ce0-83ac-82aea01c477d",
        "plantName": "Hartweg's Paspalum",
        "scientificName": "Paspalum hartwegianum Fourn.",
        "family": "Poaceae",
        "wateringFrequency": "Often",
        "lightRequirement": "high light",
        "temperatureRange": "moderate",
        "soilType": "loamy",
        "fertilizerFrequency": "Weekly",
        "bloomingSeason": "spring",
        "height": 82.66
    },
    {
        "id": "65cb31db-70ed-4121-8a3a-19c0a82ef661",
        "plantName": "Strapfern",
        "scientificName": "Campyloneurum C. Presl",
        "family": "Polypodiaceae",
        "wateringFrequency": "Daily",
        "lightRequirement": "medium light",
        "temperatureRange": "warm",
        "soilType": "clay",
        "fertilizerFrequency": "Yearly",
        "bloomingSeason": "summer",
        "height": 22.26
    },
    {
        "id": "e962ede9-2957-4ab3-9a7d-426a3369dc0a",
        "plantName": "Western Rosinweed",
        "scientificName": "Calycadenia DC.",
        "family": "Asteraceae",
        "wateringFrequency": "Weekly",
        "lightRequirement": "medium light",
        "temperatureRange": "moderate",
        "soilType": "loamy",
        "fertilizerFrequency": "Often",
        "bloomingSeason": "spring",
        "height": 84.15
    },
    {
        "id": "1cef474c-f4be-4fb2-bf0f-7d68824d7201",
        "plantName": "Missouri Sedge",
        "scientificName": "Carex missouriensis P. Rothr. & Reznicek",
        "family": "Cyperaceae",
        "wateringFrequency": "Often",
        "lightRequirement": "medium light",
        "temperatureRange": "warm",
        "soilType": "clay",
        "fertilizerFrequency": "Never",
        "bloomingSeason": "fall",
        "height": 8.91
    },
    {
        "id": "c181c73b-f5b4-4546-bbd1-0fff9bb62277",
        "plantName": "Bog Laurel",
        "scientificName": "Kalmia polifolia Wangenh.",
        "family": "Ericaceae",
        "wateringFrequency": "Seldom",
        "lightRequirement": "high light",
        "temperatureRange": "warm",
        "soilType": "sandy",
        "fertilizerFrequency": "Yearly",
        "bloomingSeason": "fall",
        "height": 47.18
    },
    {
        "id": "a60a060c-6e09-477b-b521-ded99c2ac072",
        "plantName": "Palo Bronco",
        "scientificName": "Malpighia fucata Ker Gawl.",
        "family": "Malpighiaceae",
        "wateringFrequency": "Often",
        "lightRequirement": "low light",
        "temperatureRange": "cool",
        "soilType": "sandy",
        "fertilizerFrequency": "Once",
        "bloomingSeason": "fall",
        "height": 17.26
    },
    {
        "id": "1b662ea7-4800-4751-8824-63e85b3cfbe1",
        "plantName": "Soft Greeneyes",
        "scientificName": "Berlandiera pumila (Michx.) Nutt. var. pumila",
        "family": "Asteraceae",
        "wateringFrequency": "Daily",
        "lightRequirement": "medium light",
        "temperatureRange": "warm",
        "soilType": "sandy",
        "fertilizerFrequency": "Weekly",
        "bloomingSeason": "spring",
        "height": 43.96
    },
    {
        "id": "36624a63-4ddc-4e91-9fad-fa3e51bcac2b",
        "plantName": "Woolly Sunflower",
        "scientificName": "Constancea B.G. Baldw.",
        "family": "Asteraceae",
        "wateringFrequency": "Weekly",
        "lightRequirement": "low light",
        "temperatureRange": "cool",
        "soilType": "sandy",
        "fertilizerFrequency": "Often",
        "bloomingSeason": "fall",
        "height": 64
    },
    {
        "id": "3d8a15ed-e7c3-4f51-8777-db38d7fd63ce",
        "plantName": "King's Rosy Sandwort",
        "scientificName": "Arenaria kingii (S. Watson) M.E. Jones ssp. rosea Maguire",
        "family": "Caryophyllaceae",
        "wateringFrequency": "Never",
        "lightRequirement": "medium light",
        "temperatureRange": "cool",
        "soilType": "clay",
        "fertilizerFrequency": "Yearly",
        "bloomingSeason": "summer",
        "height": 26.14
    },
    {
        "id": "299d9713-d5af-4778-b8b7-01357ed26a8b",
        "plantName": "Pine Barren Beaksedge",
        "scientificName": "Rhynchospora pineticola C.B. Clarke",
        "family": "Cyperaceae",
        "wateringFrequency": "Often",
        "lightRequirement": "high light",
        "temperatureRange": "moderate",
        "soilType": "sandy",
        "fertilizerFrequency": "Yearly",
        "bloomingSeason": "summer",
        "height": 10.71
    },
    {
        "id": "229b0335-3a60-4412-9502-689c3454af5b",
        "plantName": "Hawai'i Bog Orchid",
        "scientificName": "Platanthera holochila (Hillebr.) Kraenzlin",
        "family": "Orchidaceae",
        "wateringFrequency": "Daily",
        "lightRequirement": "low light",
        "temperatureRange": "warm",
        "soilType": "loamy",
        "fertilizerFrequency": "Often",
        "bloomingSeason": "winter",
        "height": 10.83
    },
    {
        "id": "6f84c2b3-a248-4791-8b04-68cd95a0139c",
        "plantName": "Amazonian Coca",
        "scientificName": "Erythroxylum coca Lam. var. ipadu Plowman",
        "family": "Erythroxylaceae",
        "wateringFrequency": "Often",
        "lightRequirement": "medium light",
        "temperatureRange": "cool",
        "soilType": "sandy",
        "fertilizerFrequency": "Once",
        "bloomingSeason": "fall",
        "height": 33.11
    },
    {
        "id": "961792e0-ded5-4b16-92dc-7e4544666e30",
        "plantName": "Wild Coffee-bean",
        "scientificName": "Bauhinia petersiana Bolle ssp. macrantha (Oliv.) Brummitt & J.H. Ross",
        "family": "Fabaceae",
        "wateringFrequency": "Daily",
        "lightRequirement": "high light",
        "temperatureRange": "cool",
        "soilType": "clay",
        "fertilizerFrequency": "Monthly",
        "bloomingSeason": "summer",
        "height": 88.04
    },
    {
        "id": "2a906082-0d0b-453a-92b0-fab0179685e8",
        "plantName": "Milfoil Wattle",
        "scientificName": "Acacia millefolia S. Watson",
        "family": "Fabaceae",
        "wateringFrequency": "Seldom",
        "lightRequirement": "high light",
        "temperatureRange": "cool",
        "soilType": "clay",
        "fertilizerFrequency": "Yearly",
        "bloomingSeason": "summer",
        "height": 24.08
    },
    {
        "id": "b6287ad9-5f7a-4998-a416-2d34ad57d2a2",
        "plantName": "Mogollon Hawkweed",
        "scientificName": "Hieracium fendleri Sch. Bip. var. mogollense A. Gray",
        "family": "Asteraceae",
        "wateringFrequency": "Yearly",
        "lightRequirement": "medium light",
        "temperatureRange": "moderate",
        "soilType": "sandy",
        "fertilizerFrequency": "Often",
        "bloomingSeason": "summer",
        "height": 11.73
    },
    {
        "id": "a34c9c3e-1347-4c6a-b1bd-ea626be8094d",
        "plantName": "Mojave Panicgrass",
        "scientificName": "Panicum mohavense J. Reeder",
        "family": "Poaceae",
        "wateringFrequency": "Monthly",
        "lightRequirement": "high light",
        "temperatureRange": "moderate",
        "soilType": "sandy",
        "fertilizerFrequency": "Weekly",
        "bloomingSeason": "spring",
        "height": 16.31
    },
    {
        "id": "9142eee8-31a7-46e8-a6e8-763c4bcf26b3",
        "plantName": "Green Fly Orchid",
        "scientificName": "Epidendrum magnoliae Muhl. var. magnoliae",
        "family": "Orchidaceae",
        "wateringFrequency": "Weekly",
        "lightRequirement": "high light",
        "temperatureRange": "moderate",
        "soilType": "loamy",
        "fertilizerFrequency": "Yearly",
        "bloomingSeason": "spring",
        "height": 13.12
    },
    {
        "id": "7d417a6f-feaa-4764-8042-cca968ac5ae3",
        "plantName": "Alpine Woodfern",
        "scientificName": "Dryopteris wallichiana (Spreng.) Hyl.",
        "family": "Dryopteridaceae",
        "wateringFrequency": "Often",
        "lightRequirement": "low light",
        "temperatureRange": "warm",
        "soilType": "sandy",
        "fertilizerFrequency": "Monthly",
        "bloomingSeason": "spring",
        "height": 32.49
    },
    {
        "id": "ec3b0de5-790b-4042-b114-9bac07817be4",
        "plantName": "Compact Penstemon",
        "scientificName": "Penstemon compactus (D.D. Keck) Crosswh.",
        "family": "Scrophulariaceae",
        "wateringFrequency": "Weekly",
        "lightRequirement": "low light",
        "temperatureRange": "moderate",
        "soilType": "loamy",
        "fertilizerFrequency": "Daily",
        "bloomingSeason": "summer",
        "height": 3.59
    },
    {
        "id": "0782e16c-7e8a-4492-a2fd-509164c3c26a",
        "plantName": "Triangle Cactus",
        "scientificName": "Acanthocereus tetragonus (L.) Humm.",
        "family": "Cactaceae",
        "wateringFrequency": "Seldom",
        "lightRequirement": "high light",
        "temperatureRange": "cool",
        "soilType": "sandy",
        "fertilizerFrequency": "Yearly",
        "bloomingSeason": "summer",
        "height": 14.68
    },
    {
        "id": "2926d5a4-cbfe-4cf2-92fa-67904234f05d",
        "plantName": "Sandcherry",
        "scientificName": "Prunus pumila L.",
        "family": "Rosaceae",
        "wateringFrequency": "Often",
        "lightRequirement": "low light",
        "temperatureRange": "moderate",
        "soilType": "sandy",
        "fertilizerFrequency": "Daily",
        "bloomingSeason": "fall",
        "height": 7.98
    },
    {
        "id": "a9b5c33a-c071-4ac5-a93b-82ffb9aa6d4e",
        "plantName": "Canadian Lousewort",
        "scientificName": "Pedicularis canadensis L.",
        "family": "Scrophulariaceae",
        "wateringFrequency": "Once",
        "lightRequirement": "high light",
        "temperatureRange": "warm",
        "soilType": "clay",
        "fertilizerFrequency": "Once",
        "bloomingSeason": "summer",
        "height": 58.29
    },
    {
        "id": "533ba4fe-2a09-42e8-ad71-3275fcc0c3f0",
        "plantName": "Indian Headdress",
        "scientificName": "Tracyina S.F. Blake",
        "family": "Asteraceae",
        "wateringFrequency": "Daily",
        "lightRequirement": "low light",
        "temperatureRange": "warm",
        "soilType": "clay",
        "fertilizerFrequency": "Once",
        "bloomingSeason": "summer",
        "height": 48.11
    },
    {
        "id": "3e2c44b0-baec-4d95-bf99-e5f3d79d5c72",
        "plantName": "Yellow Water Buttercup",
        "scientificName": "Ranunculus flabellaris Raf.",
        "family": "Ranunculaceae",
        "wateringFrequency": "Monthly",
        "lightRequirement": "medium light",
        "temperatureRange": "cool",
        "soilType": "loamy",
        "fertilizerFrequency": "Never",
        "bloomingSeason": "winter",
        "height": 50.77
    },
    {
        "id": "74cc9e23-8fb8-4f71-8268-6b78d5719e11",
        "plantName": "Green Deathcamas",
        "scientificName": "Zigadenus virescens (Kunth) J.F. Macbr.",
        "family": "Liliaceae",
        "wateringFrequency": "Yearly",
        "lightRequirement": "medium light",
        "temperatureRange": "moderate",
        "soilType": "loamy",
        "fertilizerFrequency": "Seldom",
        "bloomingSeason": "spring",
        "height": 25.62
    },
    {
        "id": "ebfc0cb4-0e24-49dc-ba9d-8dff2ac96ad2",
        "plantName": "Serrate Ptychomitrium Moss",
        "scientificName": "Ptychomitrium serratum (Müll. Hal.) Bruch & Schimp.",
        "family": "Ptychomitriaceae",
        "wateringFrequency": "Never",
        "lightRequirement": "high light",
        "temperatureRange": "warm",
        "soilType": "loamy",
        "fertilizerFrequency": "Weekly",
        "bloomingSeason": "spring",
        "height": 75.99
    },
    {
        "id": "737e345e-ebff-4997-8f2b-529bf45f58d9",
        "plantName": "Poison Sanicle",
        "scientificName": "Sanicula bipinnata Hook. & Arn.",
        "family": "Apiaceae",
        "wateringFrequency": "Once",
        "lightRequirement": "medium light",
        "temperatureRange": "warm",
        "soilType": "loamy",
        "fertilizerFrequency": "Monthly",
        "bloomingSeason": "spring",
        "height": 9.77
    },
    {
        "id": "d758b566-c4a1-4736-8fb0-410670db53ef",
        "plantName": "Kaibab Agave",
        "scientificName": "Agave utahensis Engelm. var. kaibabensis (McKelvey) Breitung",
        "family": "Agavaceae",
        "wateringFrequency": "Weekly",
        "lightRequirement": "medium light",
        "temperatureRange": "warm",
        "soilType": "sandy",
        "fertilizerFrequency": "Seldom",
        "bloomingSeason": "winter",
        "height": 54.41
    },
    {
        "id": "321c57c0-248d-42cf-a103-81d3821db3ab",
        "plantName": "Peppermint Drop Lichen",
        "scientificName": "Icmadophila ericetorum (L.) Zahlbr.",
        "family": "Baeomycetaceae",
        "wateringFrequency": "Often",
        "lightRequirement": "low light",
        "temperatureRange": "warm",
        "soilType": "loamy",
        "fertilizerFrequency": "Once",
        "bloomingSeason": "winter",
        "height": 19.53
    },
    {
        "id": "e0853769-d00e-4367-8f29-563ff1d8f47c",
        "plantName": "Scotch Laburnum",
        "scientificName": "Laburnum alpinum (Mill.) J. Presl",
        "family": "Fabaceae",
        "wateringFrequency": "Daily",
        "lightRequirement": "low light",
        "temperatureRange": "warm",
        "soilType": "clay",
        "fertilizerFrequency": "Weekly",
        "bloomingSeason": "spring",
        "height": 20.84
    },
    {
        "id": "58a878ba-0fb6-4e10-bc23-b4fdfd97a0c8",
        "plantName": "Thelidium Lichen",
        "scientificName": "Thelidium areolatum J.W. Thomson",
        "family": "Verrucariaceae",
        "wateringFrequency": "Yearly",
        "lightRequirement": "medium light",
        "temperatureRange": "moderate",
        "soilType": "sandy",
        "fertilizerFrequency": "Seldom",
        "bloomingSeason": "spring",
        "height": 39.54
    },
    {
        "id": "a890d11f-5990-4729-813b-d9cf10e123b5",
        "plantName": "Blistered Navel Lichen",
        "scientificName": "Lasallia pustulata (L.) Mérat",
        "family": "Umbilicariaceae",
        "wateringFrequency": "Seldom",
        "lightRequirement": "low light",
        "temperatureRange": "cool",
        "soilType": "loamy",
        "fertilizerFrequency": "Once",
        "bloomingSeason": "winter",
        "height": 70.18
    },
    {
        "id": "7f02b734-9ba3-4b81-b321-80a16de39ce2",
        "plantName": "Whitebark Senna",
        "scientificName": "Senna bacillaris (L. f.) Irwin & Barneby",
        "family": "Fabaceae",
        "wateringFrequency": "Often",
        "lightRequirement": "medium light",
        "temperatureRange": "warm",
        "soilType": "sandy",
        "fertilizerFrequency": "Once",
        "bloomingSeason": "winter",
        "height": 68.35
    },
    {
        "id": "39583365-4190-43ed-a692-ffdbce71bd9a",
        "plantName": "Shaggyfruit Pepperweed",
        "scientificName": "Lepidium lasiocarpum Nutt. var. lasiocarpum",
        "family": "Brassicaceae",
        "wateringFrequency": "Often",
        "lightRequirement": "medium light",
        "temperatureRange": "warm",
        "soilType": "clay",
        "fertilizerFrequency": "Never",
        "bloomingSeason": "winter",
        "height": 38.48
    },
    {
        "id": "e2ac182d-1da7-4875-9071-98df73a88a2a",
        "plantName": "Rim Lichen",
        "scientificName": "Lecanora atrosulphurea (Wahlenb.) Ach.",
        "family": "Lecanoraceae",
        "wateringFrequency": "Monthly",
        "lightRequirement": "high light",
        "temperatureRange": "warm",
        "soilType": "loamy",
        "fertilizerFrequency": "Daily",
        "bloomingSeason": "summer",
        "height": 6.86
    },
    {
        "id": "100d5894-977b-4c9f-8680-2324b392bc94",
        "plantName": "Sherman Hoyt Woolstar",
        "scientificName": "Eriastrum pluriflorum (A. Heller) H. Mason ssp. sherman-hoytae (Craig) H. Mason",
        "family": "Polemoniaceae",
        "wateringFrequency": "Yearly",
        "lightRequirement": "low light",
        "temperatureRange": "moderate",
        "soilType": "sandy",
        "fertilizerFrequency": "Yearly",
        "bloomingSeason": "spring",
        "height": 80.11
    },
    {
        "id": "13157f69-5795-4d06-9d2d-7f8c8933d38b",
        "plantName": "Hybrid Locust",
        "scientificName": "Robinia ×longiloba Ashe (pro sp.)",
        "family": "Fabaceae",
        "wateringFrequency": "Weekly",
        "lightRequirement": "medium light",
        "temperatureRange": "cool",
        "soilType": "clay",
        "fertilizerFrequency": "Often",
        "bloomingSeason": "summer",
        "height": 6.66
    },
    {
        "id": "c44a061c-0e4c-463f-a946-fb2f46fb87c9",
        "plantName": "Mississippi River Wakerobin",
        "scientificName": "Trillium foetidissimum J.D. Freeman",
        "family": "Liliaceae",
        "wateringFrequency": "Never",
        "lightRequirement": "low light",
        "temperatureRange": "cool",
        "soilType": "sandy",
        "fertilizerFrequency": "Weekly",
        "bloomingSeason": "spring",
        "height": 98.16
    },
    {
        "id": "7e79fb7f-b8da-40fb-8827-29f6cd906b10",
        "plantName": "Calliscirpus",
        "scientificName": "Calliscirpus C.N. Gilmour, J.R. Starr & Naczi",
        "family": "Cyperaceae",
        "wateringFrequency": "Seldom",
        "lightRequirement": "high light",
        "temperatureRange": "warm",
        "soilType": "clay",
        "fertilizerFrequency": "Daily",
        "bloomingSeason": "winter",
        "height": 30.83
    },
    {
        "id": "d0eec4c3-9fc9-4c55-9942-f9a0b92daa04",
        "plantName": "Largefruit Amaranth",
        "scientificName": "Amaranthus deflexus L.",
        "family": "Amaranthaceae",
        "wateringFrequency": "Monthly",
        "lightRequirement": "high light",
        "temperatureRange": "moderate",
        "soilType": "loamy",
        "fertilizerFrequency": "Often",
        "bloomingSeason": "spring",
        "height": 30.59
    },
    {
        "id": "7f1be86a-dc71-4562-a276-b886fc62a88a",
        "plantName": "Dwarf Checkerbloom",
        "scientificName": "Sidalcea celata (Jeps.) S.R. Hill",
        "family": "Malvaceae",
        "wateringFrequency": "Monthly",
        "lightRequirement": "medium light",
        "temperatureRange": "warm",
        "soilType": "clay",
        "fertilizerFrequency": "Monthly",
        "bloomingSeason": "fall",
        "height": 75.96
    },
    {
        "id": "7eaaf896-4625-4db8-ad13-62c38494162d",
        "plantName": "Illinois Ticktrefoil",
        "scientificName": "Desmodium illinoense A. Gray",
        "family": "Fabaceae",
        "wateringFrequency": "Once",
        "lightRequirement": "medium light",
        "temperatureRange": "warm",
        "soilType": "sandy",
        "fertilizerFrequency": "Weekly",
        "bloomingSeason": "fall",
        "height": 63.54
    },
    {
        "id": "c8ad2da5-cdb6-48c8-95b1-fb9a40f2201c",
        "plantName": "Sansevieria",
        "scientificName": "Sansevieria Thunb.",
        "family": "Agavaceae",
        "wateringFrequency": "Weekly",
        "lightRequirement": "high light",
        "temperatureRange": "cool",
        "soilType": "clay",
        "fertilizerFrequency": "Monthly",
        "bloomingSeason": "summer",
        "height": 77.22
    },
    {
        "id": "042fb7c6-b958-4133-90e8-490b026651c3",
        "plantName": "Clustered Pellitory",
        "scientificName": "Parietaria praetermissa Hinton",
        "family": "Urticaceae",
        "wateringFrequency": "Often",
        "lightRequirement": "medium light",
        "temperatureRange": "cool",
        "soilType": "sandy",
        "fertilizerFrequency": "Daily",
        "bloomingSeason": "summer",
        "height": 77.09
    },
    {
        "id": "099fa4a1-df7b-4384-b0a9-773845ba8efd",
        "plantName": "Slendertube Skyrocket",
        "scientificName": "Ipomopsis tenuituba (Rydb.) V.E. Grant",
        "family": "Polemoniaceae",
        "wateringFrequency": "Often",
        "lightRequirement": "high light",
        "temperatureRange": "cool",
        "soilType": "loamy",
        "fertilizerFrequency": "Monthly",
        "bloomingSeason": "summer",
        "height": 16.47
    },
    {
        "id": "727010fb-a9ff-43db-ba48-8d652eda4b47",
        "plantName": "Rough Hedgenettle",
        "scientificName": "Stachys rigida Nutt. ex Benth.",
        "family": "Lamiaceae",
        "wateringFrequency": "Yearly",
        "lightRequirement": "medium light",
        "temperatureRange": "moderate",
        "soilType": "clay",
        "fertilizerFrequency": "Monthly",
        "bloomingSeason": "summer",
        "height": 1.74
    },
    {
        "id": "7079e205-99c2-4184-960b-2238902e41dd",
        "plantName": "Schimper's Acaulon Moss",
        "scientificName": "Acaulon schimperianum (Sull.) Sull.",
        "family": "Pottiaceae",
        "wateringFrequency": "Yearly",
        "lightRequirement": "high light",
        "temperatureRange": "cool",
        "soilType": "clay",
        "fertilizerFrequency": "Never",
        "bloomingSeason": "spring",
        "height": 24.7
    },
    {
        "id": "73a5e1ef-5ea5-4dca-827e-4650ac6d83dd",
        "plantName": "Rayless Sunflower",
        "scientificName": "Helianthus radula (Pursh) Torr. & A. Gray",
        "family": "Asteraceae",
        "wateringFrequency": "Seldom",
        "lightRequirement": "high light",
        "temperatureRange": "cool",
        "soilType": "clay",
        "fertilizerFrequency": "Seldom",
        "bloomingSeason": "spring",
        "height": 63.83
    },
    {
        "id": "b3df8032-f6f9-4e7f-b338-6bedaf722c90",
        "plantName": "Tievine",
        "scientificName": "Ipomoea cordatotriloba Dennst.",
        "family": "Convolvulaceae",
        "wateringFrequency": "Never",
        "lightRequirement": "medium light",
        "temperatureRange": "warm",
        "soilType": "sandy",
        "fertilizerFrequency": "Seldom",
        "bloomingSeason": "fall",
        "height": 3.67
    },
    {
        "id": "4502eff3-099a-41f8-b5ca-d0c546792dc1",
        "plantName": "Rough Chervil",
        "scientificName": "Chaerophyllum temulum L.",
        "family": "Apiaceae",
        "wateringFrequency": "Often",
        "lightRequirement": "high light",
        "temperatureRange": "warm",
        "soilType": "sandy",
        "fertilizerFrequency": "Weekly",
        "bloomingSeason": "fall",
        "height": 37.41
    },
    {
        "id": "d1cc5ce9-2a07-4b4e-b3a0-9721c376dc27",
        "plantName": "Compact Earth Lichen",
        "scientificName": "Catapyrenium compactum (A. Massal.) R. Sant.",
        "family": "Verrucariaceae",
        "wateringFrequency": "Once",
        "lightRequirement": "low light",
        "temperatureRange": "moderate",
        "soilType": "sandy",
        "fertilizerFrequency": "Often",
        "bloomingSeason": "spring",
        "height": 88.64
    },
    {
        "id": "ac53e2a7-0409-47ab-81b8-b3e375c82876",
        "plantName": "Douglass' Springparsley",
        "scientificName": "Cymopterus douglassii R.L. Hartm. & Constance",
        "family": "Apiaceae",
        "wateringFrequency": "Once",
        "lightRequirement": "high light",
        "temperatureRange": "warm",
        "soilType": "sandy",
        "fertilizerFrequency": "Daily",
        "bloomingSeason": "winter",
        "height": 35.14
    },
    {
        "id": "b4fbf3e8-642a-4dbb-9204-762a3ce3158c",
        "plantName": "Calycocarpum",
        "scientificName": "Calycocarpum (Nutt.) Spach",
        "family": "Menispermaceae",
        "wateringFrequency": "Once",
        "lightRequirement": "low light",
        "temperatureRange": "moderate",
        "soilType": "clay",
        "fertilizerFrequency": "Seldom",
        "bloomingSeason": "winter",
        "height": 83.22
    },
    {
        "id": "d0cfb9d6-3f55-426d-8d2d-58ae3260b68f",
        "plantName": "Bayrumtree",
        "scientificName": "Pimenta racemosa (Mill.) J.W. Moore var. grisea (Kiaersk.) Fosberg",
        "family": "Myrtaceae",
        "wateringFrequency": "Daily",
        "lightRequirement": "high light",
        "temperatureRange": "cool",
        "soilType": "sandy",
        "fertilizerFrequency": "Seldom",
        "bloomingSeason": "fall",
        "height": 56.81
    },
    {
        "id": "344166b8-305f-409f-8b39-fdf7460081ec",
        "plantName": "Radford's Balm",
        "scientificName": "Dicerandra radfordiana R.B. Huck",
        "family": "Lamiaceae",
        "wateringFrequency": "Never",
        "lightRequirement": "low light",
        "temperatureRange": "cool",
        "soilType": "sandy",
        "fertilizerFrequency": "Once",
        "bloomingSeason": "spring",
        "height": 88.93
    },
    {
        "id": "734c3d16-e94c-4375-8aa1-be8881511b03",
        "plantName": "Dicranum Moss",
        "scientificName": "Dicranum majus Sm. var. orthophyllum A. Br. ex Milde",
        "family": "Dicranaceae",
        "wateringFrequency": "Often",
        "lightRequirement": "medium light",
        "temperatureRange": "cool",
        "soilType": "sandy",
        "fertilizerFrequency": "Daily",
        "bloomingSeason": "fall",
        "height": 94.93
    },
    {
        "id": "be744a6e-db73-42e3-a8ce-363530f98d38",
        "plantName": "Mexican Bush Sage",
        "scientificName": "Salvia leucantha Cav.",
        "family": "Lamiaceae",
        "wateringFrequency": "Yearly",
        "lightRequirement": "medium light",
        "temperatureRange": "moderate",
        "soilType": "clay",
        "fertilizerFrequency": "Once",
        "bloomingSeason": "summer",
        "height": 13.51
    },
    {
        "id": "e2a881e8-e4a7-4fbf-892d-66c04ef97122",
        "plantName": "Jasmine",
        "scientificName": "Jasminum L.",
        "family": "Oleaceae",
        "wateringFrequency": "Weekly",
        "lightRequirement": "low light",
        "temperatureRange": "moderate",
        "soilType": "loamy",
        "fertilizerFrequency": "Daily",
        "bloomingSeason": "fall",
        "height": 70.93
    },
    {
        "id": "4df512be-4368-4d07-81fe-5e90231a98e6",
        "plantName": "Prairie Fleabane",
        "scientificName": "Erigeron strigosus Muhl. ex Willd. var. strigosus",
        "family": "Asteraceae",
        "wateringFrequency": "Often",
        "lightRequirement": "high light",
        "temperatureRange": "moderate",
        "soilType": "loamy",
        "fertilizerFrequency": "Seldom",
        "bloomingSeason": "summer",
        "height": 98.17
    },
    {
        "id": "750e8458-a577-4ecc-8934-ae918fea7167",
        "plantName": "Parry's Rabbitbrush",
        "scientificName": "Ericameria parryi (A. Gray) G.L. Nesom & Baird var. affinis (A. Nelson) G.L. Nesom & Baird",
        "family": "Asteraceae",
        "wateringFrequency": "Never",
        "lightRequirement": "high light",
        "temperatureRange": "warm",
        "soilType": "sandy",
        "fertilizerFrequency": "Monthly",
        "bloomingSeason": "summer",
        "height": 65.85
    },
    {
        "id": "cdd281f0-db3a-4734-8272-14e75de4e6f0",
        "plantName": "Wreath Lichen",
        "scientificName": "Phaeophyscia orbicularis (Neck.) Moberg",
        "family": "Physciaceae",
        "wateringFrequency": "Yearly",
        "lightRequirement": "medium light",
        "temperatureRange": "warm",
        "soilType": "sandy",
        "fertilizerFrequency": "Weekly",
        "bloomingSeason": "fall",
        "height": 72.45
    },
    {
        "id": "8f414896-8489-489a-8e73-b682c0346611",
        "plantName": "Thickspike Wheatgrass",
        "scientificName": "Elymus lanceolatus (Scribn. & J.G. Sm.) Gould ssp. lanceolatus",
        "family": "Poaceae",
        "wateringFrequency": "Monthly",
        "lightRequirement": "high light",
        "temperatureRange": "cool",
        "soilType": "sandy",
        "fertilizerFrequency": "Often",
        "bloomingSeason": "fall",
        "height": 55.11
    },
    {
        "id": "cdc3eec0-d593-47e3-9bc1-ecdad5396d49",
        "plantName": "Lionsheart",
        "scientificName": "Physostegia Benth.",
        "family": "Lamiaceae",
        "wateringFrequency": "Once",
        "lightRequirement": "low light",
        "temperatureRange": "warm",
        "soilType": "clay",
        "fertilizerFrequency": "Daily",
        "bloomingSeason": "winter",
        "height": 22.21
    },
    {
        "id": "903e63e7-a1c3-4c0b-8ec0-c5a1ca24960e",
        "plantName": "Boggs Lake Dodder",
        "scientificName": "Cuscuta howelliana P. Rubtzov",
        "family": "Cuscutaceae",
        "wateringFrequency": "Seldom",
        "lightRequirement": "high light",
        "temperatureRange": "moderate",
        "soilType": "loamy",
        "fertilizerFrequency": "Seldom",
        "bloomingSeason": "winter",
        "height": 14.47
    },
    {
        "id": "ce2c7316-dfa1-4153-8b62-738e20cb5603",
        "plantName": "European Wallflower",
        "scientificName": "Erysimum hieraciifolium L.",
        "family": "Brassicaceae",
        "wateringFrequency": "Yearly",
        "lightRequirement": "high light",
        "temperatureRange": "moderate",
        "soilType": "clay",
        "fertilizerFrequency": "Never",
        "bloomingSeason": "winter",
        "height": 82.27
    },
    {
        "id": "8f988963-dfa6-4410-8a5c-d1498d83d12d",
        "plantName": "Arrowhead",
        "scientificName": "Sagittaria sagittifolia L. [excluded]",
        "family": "Alismataceae",
        "wateringFrequency": "Daily",
        "lightRequirement": "high light",
        "temperatureRange": "warm",
        "soilType": "sandy",
        "fertilizerFrequency": "Daily",
        "bloomingSeason": "fall",
        "height": 73.77
    },
    {
        "id": "85937c70-7c8c-4514-96ca-21f64806dc2c",
        "plantName": "Cracked Lichen",
        "scientificName": "Acarospora peliscypha Th. Fr.",
        "family": "Acarosporaceae",
        "wateringFrequency": "Yearly",
        "lightRequirement": "high light",
        "temperatureRange": "moderate",
        "soilType": "clay",
        "fertilizerFrequency": "Daily",
        "bloomingSeason": "winter",
        "height": 88.64
    },
    {
        "id": "edfb6af6-1732-4b6a-954c-dc6f87b1e349",
        "plantName": "Yellow Marsh Saxifrage",
        "scientificName": "Saxifraga hirculus L. ssp. propinqua (R. Br.) Á. Löve & D. Löve",
        "family": "Saxifragaceae",
        "wateringFrequency": "Once",
        "lightRequirement": "high light",
        "temperatureRange": "cool",
        "soilType": "sandy",
        "fertilizerFrequency": "Once",
        "bloomingSeason": "fall",
        "height": 44.23
    },
    {
        "id": "490e67a1-aa6c-45c4-860a-18a2399164b7",
        "plantName": "Cliff Morning-glory",
        "scientificName": "Ipomoea rupicola House",
        "family": "Convolvulaceae",
        "wateringFrequency": "Monthly",
        "lightRequirement": "high light",
        "temperatureRange": "cool",
        "soilType": "loamy",
        "fertilizerFrequency": "Often",
        "bloomingSeason": "fall",
        "height": 56.01
    },
    {
        "id": "7356abf8-757a-46b6-8030-c69d9aff24d5",
        "plantName": "Gholson's Spider-lily",
        "scientificName": "Hymenocallis gholsonii G. Lom. Sm. & Garland",
        "family": "Liliaceae",
        "wateringFrequency": "Weekly",
        "lightRequirement": "low light",
        "temperatureRange": "cool",
        "soilType": "sandy",
        "fertilizerFrequency": "Daily",
        "bloomingSeason": "fall",
        "height": 98.55
    },
    {
        "id": "fc6dd221-01be-46e8-bcd2-f7cd5d7b1cbe",
        "plantName": "Delta Eryngo",
        "scientificName": "Eryngium racemosum Jeps.",
        "family": "Apiaceae",
        "wateringFrequency": "Seldom",
        "lightRequirement": "high light",
        "temperatureRange": "moderate",
        "soilType": "sandy",
        "fertilizerFrequency": "Often",
        "bloomingSeason": "winter",
        "height": 3.13
    },
    {
        "id": "8343f71b-620d-4d83-b6fb-62e2eec7e9b0",
        "plantName": "Earleaf Bladderpod",
        "scientificName": "Lesquerella auriculata (Engelm. & A. Gray) S. Watson",
        "family": "Brassicaceae",
        "wateringFrequency": "Yearly",
        "lightRequirement": "medium light",
        "temperatureRange": "cool",
        "soilType": "sandy",
        "fertilizerFrequency": "Never",
        "bloomingSeason": "winter",
        "height": 58.38
    }
]
